trtokenizer/__init__.py
trtokenizer/errors.py
trtokenizer/tr_non_suffixes
trtokenizer/tr_tokenizer.py
trtokenizer-0.0.3.dist-info/LICENSE.txt
trtokenizer-0.0.3.dist-info/METADATA
trtokenizer-0.0.3.dist-info/WHEEL
trtokenizer-0.0.3.dist-info/top_level.txt
trtokenizer-0.0.3.dist-info/RECORD
