Metadata-Version: 2.1
Name: trtokenizer
Version: 0.0.3
Summary: Sentence and word tokenizers for the Turkish language
Home-page: https://github.com/apdullahyayik/TrTokenizer
Author: Apdullah YAYIK
Author-email: apdullahyayik@gmail.com
License: MIT
Download-URL: https://github.com/apdullahyayik/TrTokenizer/archive/refs/tags/0.0.3.tar.gz
Keywords: sentence tokenizer,word tokenizer,Turkish language,natural language processing
Platform: UNKNOWN
Requires-Python: >=3.4
License-File: LICENSE.txt
Requires-Dist: regex
